tl100/__init__.py
tl100/main.py
tl100-0.0.2.dist-info/LICENSE
tl100-0.0.2.dist-info/METADATA
tl100-0.0.2.dist-info/WHEEL
tl100-0.0.2.dist-info/top_level.txt
tl100-0.0.2.dist-info/RECORD
