Metadata-Version: 2.1
Name: tl100
Version: 0.0.2
Summary: Beurer TL100
Home-page: https://github.com/azac/tl100
Author: AZ
Author-email: adrian.zandberg@gmail.com
License: UNKNOWN
Platform: UNKNOWN
Classifier: Programming Language :: Python :: 2
Classifier: License :: Public Domain
Classifier: Operating System :: POSIX :: Linux
Requires-Python: >=2.7
Requires-Dist: pexpect
